odoo10_addon_mgmtsystem_action-10.0.1.0.0-py2.7-nspkg.pth
odoo/addons/mgmtsystem_action/README.rst
odoo/addons/mgmtsystem_action/__init__.py
odoo/addons/mgmtsystem_action/__manifest__.py
odoo/addons/mgmtsystem_action/data/action_sequence.xml
odoo/addons/mgmtsystem_action/data/automated_reminder.xml
odoo/addons/mgmtsystem_action/data/email_template.xml
odoo/addons/mgmtsystem_action/data/mgmtsystem_action_stage.xml
odoo/addons/mgmtsystem_action/demo/mgmtsystem_action.xml
odoo/addons/mgmtsystem_action/i18n/am.po
odoo/addons/mgmtsystem_action/i18n/ca.po
odoo/addons/mgmtsystem_action/i18n/de.po
odoo/addons/mgmtsystem_action/i18n/el_GR.po
odoo/addons/mgmtsystem_action/i18n/es.po
odoo/addons/mgmtsystem_action/i18n/es_ES.po
odoo/addons/mgmtsystem_action/i18n/fi.po
odoo/addons/mgmtsystem_action/i18n/fr.po
odoo/addons/mgmtsystem_action/i18n/gl.po
odoo/addons/mgmtsystem_action/i18n/hu.po
odoo/addons/mgmtsystem_action/i18n/it.po
odoo/addons/mgmtsystem_action/i18n/lv.po
odoo/addons/mgmtsystem_action/i18n/mgmtsystem_action.pot
odoo/addons/mgmtsystem_action/i18n/nb.po
odoo/addons/mgmtsystem_action/i18n/nl.po
odoo/addons/mgmtsystem_action/i18n/nn.po
odoo/addons/mgmtsystem_action/i18n/pt.po
odoo/addons/mgmtsystem_action/i18n/pt_BR.po
odoo/addons/mgmtsystem_action/i18n/pt_PT.po
odoo/addons/mgmtsystem_action/i18n/sl.po
odoo/addons/mgmtsystem_action/i18n/sv.po
odoo/addons/mgmtsystem_action/i18n/th.po
odoo/addons/mgmtsystem_action/i18n/tr.po
odoo/addons/mgmtsystem_action/i18n/vi.po
odoo/addons/mgmtsystem_action/migrations/6.1.1.0/openupgrade_analysis.txt
odoo/addons/mgmtsystem_action/migrations/7.0.1.0/post-migration.py
odoo/addons/mgmtsystem_action/migrations/7.0.1.0/pre-migration.py
odoo/addons/mgmtsystem_action/models/__init__.py
odoo/addons/mgmtsystem_action/models/mgmtsystem_action.py
odoo/addons/mgmtsystem_action/models/mgmtsystem_action_stage.py
odoo/addons/mgmtsystem_action/reports/__init__.py
odoo10_addon_mgmtsystem_action-10.0.1.0.0.dist-info/DESCRIPTION.rst
odoo10_addon_mgmtsystem_action-10.0.1.0.0.dist-info/METADATA
odoo10_addon_mgmtsystem_action-10.0.1.0.0.dist-info/RECORD
odoo10_addon_mgmtsystem_action-10.0.1.0.0.dist-info/WHEEL
odoo10_addon_mgmtsystem_action-10.0.1.0.0.dist-info/metadata.json
odoo10_addon_mgmtsystem_action-10.0.1.0.0.dist-info/namespace_packages.txt
odoo10_addon_mgmtsystem_action-10.0.1.0.0.dist-info/top_level.txt
